README.md
setup.py
src/bibtex_html_citer/__init__.py
src/bibtex_html_citer/fix_citations.py
src/bibtex_html_citer.egg-info/PKG-INFO
src/bibtex_html_citer.egg-info/SOURCES.txt
src/bibtex_html_citer.egg-info/dependency_links.txt
src/bibtex_html_citer.egg-info/entry_points.txt
src/bibtex_html_citer.egg-info/requires.txt
src/bibtex_html_citer.egg-info/top_level.txt