Metadata-Version: 1.0
Name: bibtex-html-citer
Version: 1.0.0
Summary: Finds `\cite{}` text in an HTML document and replaces with a link to DOI/URL.
Home-page: http://github.com/jvivian/bibtex-html-citer
Author: John Vivian
Author-email: jtvivian@gmail.com
License: MIT
Platform: UNKNOWN
